CHANGES.txt
LICENSE
NOTICE
README.txt
bootstrap.py
buildout.cfg
setup.py
src/lovely/__init__.py
src/lovely.jsonrpc.egg-info/PKG-INFO
src/lovely.jsonrpc.egg-info/SOURCES.txt
src/lovely.jsonrpc.egg-info/dependency_links.txt
src/lovely.jsonrpc.egg-info/namespace_packages.txt
src/lovely.jsonrpc.egg-info/requires.txt
src/lovely.jsonrpc.egg-info/top_level.txt
src/lovely.jsonrpc.egg-info/zip-safe
src/lovely/jsonrpc/__init__.py
src/lovely/jsonrpc/dispatcher.py
src/lovely/jsonrpc/dispatcher.txt
src/lovely/jsonrpc/proxy.py
src/lovely/jsonrpc/proxy.txt
src/lovely/jsonrpc/testing.py
src/lovely/jsonrpc/tests.py
src/lovely/jsonrpc/tornadohandler.py
src/lovely/jsonrpc/tornadohandler.txt
src/lovely/jsonrpc/wsgi.py
src/lovely/jsonrpc/wsgi.txt