Metadata-Version: 1.0
Name: lovely.jsonrpc
Version: 0.2.1
Summary: Python JSONRPC package
Home-page: http://code.google.com/p/lovely-jsonrpc
Author: Lovely Systems GmbH
Author-email: bernddorn@gmail.com
License: Apache License 2.0
Keywords: JSON RPC JSONRPC WSGI
Platform: Any
